deeru_cmd/__init__.py
deeru_cmd/apps.py
deeru_cmd/tests.py
deeru_cmd/app_templates/MANIFEST.in-tpl
deeru_cmd/app_templates/README.rst-tpl
deeru_cmd/app_templates/apps.py-tpl
deeru_cmd/app_templates/consts.py-tpl
deeru_cmd/app_templates/empty.py-tpl
deeru_cmd/app_templates/git_add.py-tpl
deeru_cmd/app_templates/setup.py-tpl
deeru_cmd/bin/deeru_admin.py
deeru_cmd/management/__init__.py
deeru_cmd/management/base.py
deeru_cmd/management/commands/__init__.py
deeru_cmd/management/commands/install.py
deeru_cmd/management/commands/start.py
deeru_cmd/management/commands/upgrade.py
deeru_cmd/project_templates/settings_local.py-tpl
deeru_cmd/project_templates/urls_local.py-tpl
DeerU-2.0.2.dist-info/LICENSE
DeerU-2.0.2.dist-info/METADATA
DeerU-2.0.2.dist-info/WHEEL
DeerU-2.0.2.dist-info/entry_points.txt
DeerU-2.0.2.dist-info/top_level.txt
DeerU-2.0.2.dist-info/RECORD
