Metadata-Version: 2.1
Name: DeerU
Version: 2.0.2
Summary: DeerU is a content management system(DeerU 是一个开源博客系统)
Home-page: https://github.com/gojuukaze/DeerU
Author: gojuukaze
Author-email: i@ikaze.uu.me
License: GUN V3.0
Project-URL: Documentation, https://deeru.readthedocs.io
Project-URL: Source, https://github.com/gojuukaze/DeerU
Platform: UNKNOWN
Classifier: Environment :: Web Environment
Classifier: Framework :: Django
Classifier: Intended Audience :: Developers
Classifier: License :: OSI Approved :: GNU General Public License v3 (GPLv3)
Classifier: Programming Language :: Python :: 3
Classifier: Programming Language :: Python :: 3.5
Classifier: Programming Language :: Python :: 3.6
Classifier: Development Status :: 4 - Beta
Classifier: Topic :: Internet :: WWW/HTTP
Classifier: Topic :: Internet :: WWW/HTTP :: Dynamic Content
Classifier: Topic :: Internet :: WWW/HTTP :: WSGI
Classifier: Topic :: Software Development :: Libraries :: Application Frameworks
Classifier: Topic :: Software Development :: Libraries :: Python Modules
Requires-Python: >=3.6
Requires-Dist: Django (<3.0,>=2.2)
